create_cli/__init__.py
create_cli/cd_hack.py
create_cli/cli.py
create_cli-0.1.2.dist-info/entry_points.txt
create_cli-0.1.2.dist-info/WHEEL
create_cli-0.1.2.dist-info/METADATA
create_cli-0.1.2.dist-info/RECORD
